LICENSE
MANIFEST.in
README.md
setup.py
Biofuel_MyProject.egg-info/PKG-INFO
Biofuel_MyProject.egg-info/SOURCES.txt
Biofuel_MyProject.egg-info/dependency_links.txt
Biofuel_MyProject.egg-info/top_level.txt
MyProject/2.png
MyProject/Project_GUI.py
MyProject/__init__.py
MyProject/core.py
MyProject/data/.DS_Store
MyProject/data/Flash Point and Cetane Number Predictions for Fuel Compounds.xls
MyProject/tests/__init__.py
MyProject/tests/test_core.py
MyProject/tests/data/Flash Point and Cetane Number Predictions for Fuel Compounds.xls