Metadata-Version: 1.2
Name: Biofuel-MyProject
Version: 0.3.1
Summary: Predict flash point and cetane number of biofuel
Home-page: https://github.com/Zhangjt9317/Biofuel-Group-Project
Author: Jingtian Zhang, Cheng Zeng, Renlong Zheng, Chenggang Xi
Author-email: jtz9317@gmail.com
License: MIT
Project-URL: Bug Reports, https://github.com/Zhangjt9317/Biofuel-Group-Project/issues
Project-URL: Source, https://github.com/Zhangjt9317/Biofuel-Group-Project
Keywords: flash point and cetane number
Platform: UNKNOWN
